GraphPCA/__init__.py
GraphPCA/gpca.py
GraphPCA/utils.py
st_graphpca-0.1.3.dist-info/LICENSE.txt
st_graphpca-0.1.3.dist-info/METADATA
st_graphpca-0.1.3.dist-info/WHEEL
st_graphpca-0.1.3.dist-info/top_level.txt
st_graphpca-0.1.3.dist-info/RECORD
