Metadata-Version: 2.1
Name: st-graphpca
Version: 0.1.3
Summary: A fast and interpretable dimension reduction algorithm for spatial transcriptomics data.
Home-page: https://github.com/YANG-ERA/GraphPCA/tree/master
Author: Jiyuan Yang
Author-email: 599568651@qq.com
License: MIT
License-File: LICENSE.txt
Requires-Dist: numpy (==1.23.4)
Requires-Dist: pandas (==2.1.0)
Requires-Dist: matplotlib (==3.7.3)
Requires-Dist: scipy (==1.12.0)
Requires-Dist: scikit-learn (==1.4.1.post1)
Requires-Dist: networkx (==3.2.1)
Requires-Dist: scanpy (==1.9.8)
Requires-Dist: squidpy (==1.4.1)
